<?xml version="1.0" encoding="UTF-8" standalone="no"?>
<views xmlns="http://schemas.haulmont.com/cuba/view.xsd">
    <view class="com.cernol.works.entity.WorksOrderIngredient"
          extends="_local"
          name="worksOrderIngredient-view">
        <property name="rawMaterial"
                  view="_local"/>
        <property name="lineCost"/>
    </view>
    <view class="com.cernol.works.entity.WorksOrderLable"
          extends="_local"
          name="worksOrderLable-view">
        <property name="lable"
                  view="_local"/>
        <property name="lineCost"/>
    </view>
    <view class="com.cernol.works.entity.WorksOrderPacking"
          extends="_local"
          name="worksOrderPacking-view">
        <property name="container"
                  view="_local">
            <property name="packing"
                      view="_minimal"/>
        </property>
        <property name="lineCost"/>
        <property name="lineCapacity"/>
    </view>
    <view class="com.cernol.works.entity.WorksOrder"
          extends="_local"
          name="worksOrder-view">
        <property name="worksOrderPackings"
                  view="worksOrderPacking-view">
        </property>
        <property name="worksOrderIngredients"
                  view="worksOrderIngredient-view"/>
        <property name="worksOrderLables"
                  view="worksOrderLable-view"/>
        <property name="worksOrderKeys"
                  view="_local">
            <property name="manufacturingKey"
                      view="_minimal"/>
        </property>
        <property name="product"
                  view="_minimal">
            <property name="applyOverhead"/>
        </property>
        <property name="worksOrderShippers"
                  view="worksOrderShipper-view"/>
        <property name="mixer"
                  view="_local"/>
    </view>
    <view class="com.cernol.works.entity.Product"
          extends="_local"
          name="product-view">
        <property name="category"
                  view="_minimal"/>
        <property name="formula"
                  view="formula-view"/>
        <property name="specFile"
                  view="_minimal"/>
        <property name="containers"
                  view="productContainer-view">
        </property>
    </view>
    <view class="com.cernol.works.entity.Formula"
          extends="_local"
          name="formula-view">
        <property name="rawMaterial"
                  view="_local"/>
    </view>
    <view class="com.cernol.works.entity.DecantingOrderTarget"
          extends="_local"
          name="decantingOrderTarget-view">
        <property name="container"
                  view="_local"/>
    </view>
    <view class="com.cernol.works.entity.DecantingOrder"
          extends="_local"
          name="decantingOrder-view">
        <property name="decantingOrderTargets"
                  view="decantingOrderTarget-view"/>
        <property name="decantedProduct"
                  view="_minimal">
            <property name="applyOverhead"/>
        </property>
    </view>
    <view class="com.cernol.works.entity.SalesOrderRawMaterial"
          extends="_local"
          name="salesOrderRawMaterial-view">
        <property name="rawMaterial"
                  view="_local"/>
        <property name="linePrice"/>
    </view>
    <view class="com.cernol.works.entity.SalesOrderContainer"
          extends="_local"
          name="salesOrderContainer-view">
        <property name="container"
                  view="_local"/>
        <property name="linePrice"/>
    </view>
    <view class="com.cernol.works.entity.SalesOrder"
          extends="_local"
          name="salesOrder-view">
        <property name="salesOrderContainers"
                  view="salesOrderContainer-view"/>
        <property name="salesOrderRawMaterials"
                  view="salesOrderRawMaterial-view"/>
        <property name="product"
                  view="_minimal"/>
        <property name="mixer"
                  view="_minimal"/>
    </view>
    <view class="com.cernol.works.entity.StockCount"
          extends="_local"
          name="stockCount-view">
        <property name="stockCountItems"
                  view="stockCountItem-view"/>
    </view>
    <view class="com.cernol.works.entity.StockCountItem"
          extends="_local"
          name="stockCountItem-view">
        <property name="stockItem"
                  view="_minimal"/>
        <property name="adjustedQuantity"/>
        <property name="adjustedValue"/>
    </view>
    <view class="com.cernol.works.entity.StockIntakeItem"
          extends="_local"
          name="stockIntakeItem-view">
        <property name="stockItem"
                  view="_minimal"/>
        <property name="lineValue"/>
    </view>
    <view class="com.cernol.works.entity.StockIntake"
          extends="_local"
          name="stockIntake-view">
        <property name="stockIntakeItems"
                  view="stockIntakeItem-view"/>
    </view>
    <view class="com.cernol.works.entity.Formula"
          extends="_local"
          name="formula-view_with_product">
        <property name="product"
                  view="_minimal"/>
    </view>
    <view class="com.cernol.works.entity.Lable"
          extends="_local"
          name="lable-view">
        <property name="imageFile"
                  view="_local"/>
    </view>
    <view class="com.cernol.works.entity.RawMaterial"
          extends="_local"
          name="rawMaterial-view">
        <property name="specFile"
                  view="_minimal"/>
    </view>
    <view class="com.cernol.works.entity.StockItem"
          extends="_local"
          name="stockItem-view">
        <property name="codeNumber"/>
    </view>
    <view class="com.cernol.works.entity.WorksOrder"
          extends="_local"
          name="worksOrder-report-view">
    </view>
    <view class="com.cernol.works.entity.ProductContainer"
          extends="_local"
          name="productContainer-view">
        <property name="container"
                  view="_local">
        </property>
        <property name="productLabel"
                  view="_minimal"/>
        <property name="keepAwayLabel"
                  view="_minimal"/>
        <property name="poisonousLabel"
                  view="_minimal"/>
        <property name="flammableLabel"
                  view="_minimal"/>
        <property name="corrosiveLabel"
                  view="_minimal"/>
    </view>
    <view class="com.cernol.works.entity.PriceUpdateItem"
          extends="_local"
          name="priceUpdateItem-view">
        <property name="stockItem"
                  view="_minimal"/>
        <property name="priceUpdate"
                  view="_local"/>
    </view>
    <view class="com.cernol.works.entity.PriceUpdate"
          extends="_local"
          name="priceUpdate-view">
        <property name="priceUpdateItems"
                  view="_local">
            <property name="stockItem"
                      view="_minimal"/>
        </property>
    </view>
    <view class="com.cernol.works.entity.Container"
          extends="_local"
          name="container-view">
        <property name="packing"
                  view="_minimal"/>
    </view>
    <view class="com.cernol.works.entity.WorksOrderPacking"
          extends="_local"
          name="worksOrderPacking-view_1">
        <property name="worksOrder"
                  view="_minimal">
            <property name="documentOn"/>
        </property>
        <property name="container"
                  view="_minimal">
            <property name="capacity"/>
        </property>
    </view>
    <view class="com.cernol.works.entity.ProductContainer"
          extends="_local"
          name="productContainer-view_1">
        <property name="product"
                  view="_minimal"/>
        <property name="container"
                  view="_minimal"/>
    </view>
    <view class="com.cernol.works.entity.Container"
          extends="_minimal"
          name="container-view_1">
        <property name="productContainers"
                  view="_minimal"/>
        <property name="capacity"/>
    </view>
    <view class="com.cernol.works.entity.PriceList"
          extends="_local"
          name="priceList-view">
        <property name="product"
                  view="_minimal"/>
        <property name="container"
                  view="_minimal"/>
    </view>
    <view class="com.cernol.works.entity.IntermediateOrder"
          extends="_local"
          name="intermediateOrder-view">
        <property name="intermediateOrderIngredients"
                  view="intermediateOrderIngredient-view"/>
        <property name="product"
                  view="_minimal"/>
    </view>
    <view class="com.cernol.works.entity.IntermediateOrderIngredient"
          extends="_local"
          name="intermediateOrderIngredient-view">
        <property name="rawMaterial"
                  view="_local"/>
    </view>
    <view class="com.cernol.works.entity.WorksOrderKey"
          extends="_local"
          name="worksOrderKey-view">
        <property name="manufacturingKey"
                  view="_minimal"/>
    </view>
    <view class="com.cernol.works.entity.Instruction"
          extends="_local"
          name="instruction-view"/>
    <view class="com.cernol.works.entity.Packing"
          extends="_local"
          name="packing-view"/>
    <view class="com.cernol.works.entity.WorksOrderShipper"
          extends="_local"
          name="worksOrderShipper-view">
        <property name="packing"
                  view="_minimal"/>
        <property name="lineCost"/>
    </view>
</views>
